actionlogger/__init__.py
actionlogger/actionlogger.py
actionlogger/admin.py
actionlogger/apps.py
actionlogger/models.py
actionlogger/locale/pt_BR/LC_MESSAGES/django.mo
actionlogger/locale/pt_BR/LC_MESSAGES/django.po
actionlogger/migrations/0001_initial.py
actionlogger/migrations/__init__.py
actionlogger/migrations/__pycache__/0001_initial.cpython-39.pyc
actionlogger/migrations/__pycache__/__init__.cpython-39.pyc
actionlogger/tests/__init__.py
actionlogger/tests/test_actionlogger.py
identity/__init__.py
identity/apps.py
identity/forms.py
identity/keystone.py
identity/models.py
identity/urls.py
identity/views.py
identity/locale/pt_BR/LC_MESSAGES/django.mo
identity/locale/pt_BR/LC_MESSAGES/django.po
identity/migrations/0001_initial.py
identity/migrations/__init__.py
identity/migrations/__pycache__/0001_initial.cpython-39.pyc
identity/migrations/__pycache__/__init__.cpython-39.pyc
identity/static/identity/css/project.css
identity/static/identity/js/project.js
identity/templates/identity/_project_members.html
identity/templates/identity/_project_metadata.html
identity/templates/identity/project_change.html
identity/templates/identity/project_change_noteam.html
identity/templates/identity/project_create.html
identity/templates/identity/project_create_success.html
identity/templates/identity/project_delete_confirm.html
identity/templates/identity/project_edit.html
identity/templates/identity/projects.html
identity/templates/identity/projects_and_users.html
identity/templates/identity/user_create.html
identity/templates/identity/user_edit.html
identity/templates/identity/users.html
identity/tests/__init__.py
identity/tests/fakes.py
identity/tests/test_ajax_views.py
identity/tests/test_keystone.py
identity/tests/test_project_views.py
identity/tests/test_user_views.py
storage/__init__.py
storage/apps.py
storage/forms.py
storage/models.py
storage/urls.py
storage/utils.py
storage/locale/pt_BR/LC_MESSAGES/django.mo
storage/locale/pt_BR/LC_MESSAGES/django.po
vault-1.2.10.dist-info/LICENSE.txt
vault-1.2.10.dist-info/METADATA
vault-1.2.10.dist-info/WHEEL
vault-1.2.10.dist-info/top_level.txt
vault-1.2.10.dist-info/RECORD
