Metadata-Version: 2.1
Name: vault
Version: 1.2.10
Summary: Admin webapp for OpenStack Keystone and OpenStack Swift.
Home-page: https://github.com/globocom/vault
Author: Storm
Author-email: storm@g.globo
License: UNKNOWN
Platform: UNKNOWN
License-File: LICENSE.txt
Requires-Dist: Babel (==2.3.4)
Requires-Dist: gunicorn (==19.3.0)
Requires-Dist: Django (==3.1.6)
Requires-Dist: django3-all-access (==0.10.0)
Requires-Dist: iso8601 (==0.1.11)
Requires-Dist: mysqlclient (==1.4.6)
Requires-Dist: netaddr (==0.7.18)
Requires-Dist: oslo.config (==5.2.0)
Requires-Dist: python-dateutil (==2.5.3)
Requires-Dist: python-keystoneclient (==3.16.0)
Requires-Dist: python-swiftclient (==3.7.1)
Requires-Dist: pytz (==2015.4)
Requires-Dist: requests (==2.19.1)
Requires-Dist: cryptography (==2.9.2)
